bastet/__init__.py
bastet/__main__.py
bastet/config.py
bastet/py.typed
bastet/runner.py
bastet/reporting/__init__.py
bastet/reporting/abc.py
bastet/reporting/codeclimate.py
bastet/reporting/console.py
bastet/reporting/file.py
bastet/reporting/github.py
bastet/tools/__init__.py
bastet/tools/audit.py
bastet/tools/exceptions.py
bastet/tools/format.py
bastet/tools/lint.py
bastet/tools/reuse.py
bastet/tools/test.py
bastet/tools/tool.py
bastet-0.1.3.dist-info/LICENSE.md
bastet-0.1.3.dist-info/METADATA
bastet-0.1.3.dist-info/WHEEL
bastet-0.1.3.dist-info/entry_points.txt
bastet-0.1.3.dist-info/top_level.txt
bastet-0.1.3.dist-info/RECORD
