Metadata-Version: 2.2
Name: bastet
Version: 0.1.3
Summary: Bastet Python Developers Tools (https://github.com/mewbotorg/bastet)
Author-email: MewBot Org <mewbot@quicksilver.london>
Maintainer-email: MewBot Org <mewbot@quicksilver.london>
Project-URL: Source, https://github.com/mewbotorg/bastet
Classifier: Development Status :: 4 - Beta
Classifier: Intended Audience :: Developers
Classifier: Programming Language :: Python
Classifier: Programming Language :: Python :: 3.11
Classifier: Programming Language :: Python :: 3.12
Classifier: Programming Language :: Python :: 3.13
Classifier: Programming Language :: Python :: 3 :: Only
Classifier: Operating System :: OS Independent
Classifier: License :: OSI Approved :: BSD License
Requires-Python: >=3.11
License-File: LICENSE.md
Requires-Dist: colorama>=0.4.6
Requires-Dist: gitignore-parser>=0.1.11
Requires-Dist: reuse>=2.1
Requires-Dist: black>=23.1.0
Requires-Dist: flake8>=6.0.0
Requires-Dist: pylint>=2.16.0
Requires-Dist: pydocstyle>=6.3.0
Requires-Dist: isort>=5.12.0
Requires-Dist: ruff>=0.2.1
Requires-Dist: mypy>=0.991
Requires-Dist: bandit>=1.7.5
Requires-Dist: pytest>=7.1.1
Requires-Dist: pytest-asyncio~=0.21.1
Requires-Dist: pytest-cov>=3.0.0
Requires-Dist: pytest-xdist>=2.5.0
Requires-Dist: defusedxml>=0.7.1
Provides-Extra: dev
Requires-Dist: pylint-per-file-ignores; extra == "dev"
Requires-Dist: types-colorama; extra == "dev"
Requires-Dist: types-defusedxml; extra == "dev"
